dash_compose/__init__.py
dash_compose/src.py
dash_compose-2023.3.12.dist-info/LICENSE
dash_compose-2023.3.12.dist-info/METADATA
dash_compose-2023.3.12.dist-info/WHEEL
dash_compose-2023.3.12.dist-info/top_level.txt
dash_compose-2023.3.12.dist-info/RECORD
