Metadata-Version: 2.1
Name: dash-compose
Version: 2023.3.12
Summary: A tool for composing tidy Plotly Dash applications
Author-email: Elliott Wise <ell.wise@gmail.com>
License: MIT License
Project-URL: source, https://github.com/ellwise/dash-compose
Project-URL: docs, https://ellwise.github.io/dash-compose
License-File: LICENSE
Requires-Dist: dash
Provides-Extra: dev
Requires-Dist: black ; extra == 'dev'
Requires-Dist: build ; extra == 'dev'
Requires-Dist: isort ; extra == 'dev'
Requires-Dist: mkdocs-material ; extra == 'dev'
Requires-Dist: pip-tools ; extra == 'dev'
Requires-Dist: ruff ; extra == 'dev'
Requires-Dist: twine ; extra == 'dev'
